Metadata-Version: 1.1
Name: indexherbariorum
Version: 1.0.0
Summary: Python client library for Index Herbariorum API Web Services
Home-page: https://github.com/jlramirez/index-herbariorum-python-client
Author: Joel Ramirez
Author-email: joel.ramirez001@gmail.com
License: MIT License
Platform: UNKNOWN
Classifier: Development Status :: 5 - Production/Stable
Classifier: Intended Audience :: Developers
Classifier: Natural Language :: English
Classifier: License :: OSI Approved :: MIT License
Classifier: Operating System :: OS Independent
Classifier: Programming Language :: Python :: 2.7
Classifier: Programming Language :: Python :: 3.4
Classifier: Programming Language :: Python :: 3.5
Classifier: Programming Language :: Python :: 3.6
Classifier: Topic :: Software Development :: Libraries :: Python Modules
